cooplock/IResourceLock.py
cooplock/__init__.py
cooplock/resourcelock.py
cooplock-0.2.dist-info/LICENSE
cooplock-0.2.dist-info/METADATA
cooplock-0.2.dist-info/WHEEL
cooplock-0.2.dist-info/top_level.txt
cooplock-0.2.dist-info/RECORD
